{
  "parts": [
    {
      "id": 0,
      "label": "4",
      "location": [1, 4, "west"]
    },
    {
      "id": 1,
      "label": "2",
      "location": [3, 1, "north"]
    },
    {
      "id": 2,
      "label": "2",
      "location": [4, 4, "north"]
    },
    {
      "id": 3,
      "label": "2",
      "location": [5, 4, "west"]
    },
    {
      "id": 4,
      "label": "6",
      "location": [1, 5, "south"]
    },
    {
      "id": 5,
      "label": "s1",
      "location": [0, 8, "west"]
    },
    {
      "id": 6,
      "label": "3",
      "location": [1, 6, "east"]
    },
    {
      "id": 7,
      "label": "s2",
      "location": [2, 8, "west"]
    },
    {
      "id": 8,
      "label": "d1",
      "location": [3, 6, "east"]
    },
    {
      "id": 9,
      "label": "u2",
      "location": [4, 6, "east"]
    },
    {
      "id": 10,
      "label": "5",
      "location": [5, 9, "north"]
    },
    {
      "id": 11,
      "label": "3",
      "location": [5, 2, "north"]
    }
  ]
}
